professor_tools/decrypt_report.py
professor_tools/run_bench.py
professor_tools/simple_funcs.py
tests/test_grader.py
tests/test_spec_loader.py
tests/test_spec_public_key.py
tests/test_students.py
ub_grader/__init__.py
ub_grader/crypto_utils.py
ub_grader/grader.py
ub_grader/spec_loader.py
ub_grader/students.py
ub_grader-0.3.5.dist-info/METADATA
ub_grader-0.3.5.dist-info/WHEEL
ub_grader-0.3.5.dist-info/top_level.txt
ub_grader-0.3.5.dist-info/RECORD
