Metadata-Version: 2.4
Name: ub-grader
Version: 0.3.5
Summary: Librería para auto-corrección local de prácticas con reporte cifrado y firmado
Author-email: Universidad de Barcelona <noreply@example.com>
License: MIT
Project-URL: Homepage, https://example.com/ub-grader
Keywords: grading,education,encryption,autograder
Classifier: Programming Language :: Python :: 3
Classifier: Programming Language :: Python :: 3.10
Classifier: License :: OSI Approved :: MIT License
Classifier: Intended Audience :: Education
Classifier: Topic :: Education
Requires-Python: >=3.10
Requires-Dist: cryptography>=42.0.0
Provides-Extra: dev
Requires-Dist: pytest>=7.0.0; extra == "dev"
Requires-Dist: ruff>=0.5.0; extra == "dev"
Requires-Dist: pre-commit>=3.7.0; extra == "dev"
